use_case/.ipynb_checkpoints/Visualization-checkpoint.ipynb
use_case/__init__.py
use_case/Visualization.ipynb
use_case-0.2.0.dist-info/METADATA
use_case-0.2.0.dist-info/WHEEL
use_case-0.2.0.dist-info/RECORD
